cgo_email_aastudillocgo/__init__.py
cgo_email_aastudillocgo/oauth2.py
cgo_email_aastudillocgo-0.0.1.dist-info/LICENSE
cgo_email_aastudillocgo-0.0.1.dist-info/METADATA
cgo_email_aastudillocgo-0.0.1.dist-info/WHEEL
cgo_email_aastudillocgo-0.0.1.dist-info/top_level.txt
cgo_email_aastudillocgo-0.0.1.dist-info/RECORD
